relstorage/__init__.py
relstorage/_compat.py
relstorage/_inthashmap.cpp
relstorage/_inthashmap.cpython-311-x86_64-linux-gnu.so
relstorage/_inthashmap.h
relstorage/_inthashmap.pxd
relstorage/_inthashmap.pyx
relstorage/_mvcc.py
relstorage/_rs_types.h
relstorage/_rs_types.pxd
relstorage/_util.py
relstorage/component.xml
relstorage/config.py
relstorage/interfaces.py
relstorage/options.py
relstorage/pylibmc_wrapper.py
relstorage/treemark.py
relstorage/zodbconvert.py
relstorage/zodbpack.py
relstorage/zodburi_resolver.py
relstorage/adapters/__init__.py
relstorage/adapters/_util.py
relstorage/adapters/adapter.py
relstorage/adapters/batch.py
relstorage/adapters/connections.py
relstorage/adapters/connmanager.py
relstorage/adapters/dbiter.py
relstorage/adapters/drivers.py
relstorage/adapters/interfaces.py
relstorage/adapters/locker.py
relstorage/adapters/mover.py
relstorage/adapters/oidallocator.py
relstorage/adapters/packundo.py
relstorage/adapters/poller.py
relstorage/adapters/replica.py
relstorage/adapters/schema.py
relstorage/adapters/scriptrunner.py
relstorage/adapters/stats.py
relstorage/adapters/txncontrol.py
relstorage/adapters/mysql/__init__.py
relstorage/adapters/mysql/adapter.py
relstorage/adapters/mysql/connmanager.py
relstorage/adapters/mysql/locker.py
relstorage/adapters/mysql/mover.py
relstorage/adapters/mysql/oidallocator.py
relstorage/adapters/mysql/packundo.py
relstorage/adapters/mysql/schema.py
relstorage/adapters/mysql/stats.py
relstorage/adapters/mysql/txncontrol.py
relstorage/adapters/mysql/drivers/__init__.py
relstorage/adapters/mysql/drivers/_mysqldb_gevent.py
relstorage/adapters/mysql/drivers/mysqlconnector.py
relstorage/adapters/mysql/drivers/mysqldb.py
relstorage/adapters/mysql/drivers/pymysql.py
relstorage/adapters/mysql/drivers/tests/__init__.py
relstorage/adapters/mysql/drivers/tests/test_mysqldb.py
relstorage/adapters/mysql/procs/__init__.py
relstorage-4.2.0.dist-info/METADATA
relstorage-4.2.0.dist-info/WHEEL
relstorage-4.2.0.dist-info/entry_points.txt
relstorage-4.2.0.dist-info/top_level.txt
relstorage-4.2.0.dist-info/RECORD
relstorage-4.2.0.dist-info/licenses/LICENSE.txt
