Metadata-Version: 2.4
Name: RelStorage
Version: 4.2.0
Summary: A backend for ZODB that stores pickles in a relational database.
Home-page: https://relstorage.readthedocs.io/
Author: Shane Hathaway with Zope Foundation and Contributors
Author-email: shane@willowrise.com
Maintainer: Jason Madden
Maintainer-email: jason@nextthought.com
License: ZPL-2.1
Project-URL: Bug Tracker, https://github.com/zodb/relstorage/issues
Project-URL: Source Code, https://github.com/zodb/relstorage/
Project-URL: Documentation, https://relstorage.readthedocs.io
Keywords: ZODB SQL RDBMS MySQL PostgreSQL Oracle
Platform: any
Classifier: Intended Audience :: Developers
Classifier: Programming Language :: Python
Classifier: Programming Language :: Python :: 3 :: Only
Classifier: Programming Language :: Python :: 3.9
Classifier: Programming Language :: Python :: 3.10
Classifier: Programming Language :: Python :: 3.11
Classifier: Programming Language :: Python :: 3.12
Classifier: Programming Language :: Python :: 3.13
Classifier: Programming Language :: Python :: 3.14
Classifier: Programming Language :: Python :: Implementation :: CPython
Classifier: Programming Language :: Python :: Implementation :: PyPy
Classifier: Topic :: Database
Classifier: Topic :: Software Development :: Libraries :: Python Modules
Classifier: Operating System :: Microsoft :: Windows
Classifier: Operating System :: Unix
Classifier: Development Status :: 4 - Beta
Requires-Python: >=3.9
License-File: LICENSE.txt
Requires-Dist: packaging
Requires-Dist: perfmetrics>=3.0.0
Requires-Dist: zope.interface
Requires-Dist: zope.dottedname
Requires-Dist: zc.lockfile
Requires-Dist: BTrees>=4.7.2
Requires-Dist: ZODB>=5.6.0
Requires-Dist: transaction>=2.4.0
Provides-Extra: mysql
Requires-Dist: mysqlclient>=2.0.0; (platform_python_implementation == "CPython" and sys_platform != "win32") and extra == "mysql"
Requires-Dist: PyMySQL>=0.6.6; (platform_python_implementation == "PyPy" or sys_platform == "win32") and extra == "mysql"
Provides-Extra: postgresql
Requires-Dist: psycopg2>=2.8.3; platform_python_implementation == "CPython" and extra == "postgresql"
Requires-Dist: pg8000>=1.29.0; (python_version >= "3.14" and sys_platform == "win32") and platform_python_implementation == "CPython" and extra == "postgresql"
Requires-Dist: psycopg2cffi>=2.8.1; platform_python_implementation == "PyPy" and extra == "postgresql"
Provides-Extra: oracle
Requires-Dist: cx_Oracle>=6.0; extra == "oracle"
Provides-Extra: sqlite
Provides-Extra: sqlite3
Provides-Extra: memcache
Requires-Dist: pylibmc; (platform_python_implementation == "CPython" and sys_platform != "win32" and python_version < "3.12") and extra == "memcache"
Requires-Dist: python-memcached; (platform_python_implementation == "PyPy" or sys_platform == "win32") and extra == "memcache"
Provides-Extra: test
Requires-Dist: random2; extra == "test"
Requires-Dist: zope.testing; extra == "test"
Requires-Dist: ZODB[test]; extra == "test"
Requires-Dist: ZEO>=5.2; python_version > "2.7" and extra == "test"
Requires-Dist: zc.zlibstorage; extra == "test"
Requires-Dist: zope.testrunner; extra == "test"
Requires-Dist: nti.testing; extra == "test"
Requires-Dist: gevent>=23.7.0; extra == "test"
Requires-Dist: pyperf; extra == "test"
Requires-Dist: psutil; (platform_python_implementation == "CPython" or python_version != "2.7") and extra == "test"
Requires-Dist: pylibmc; (platform_python_implementation == "CPython" and sys_platform != "win32" and python_version < "3.12") and extra == "test"
Requires-Dist: python-memcached; (platform_python_implementation == "PyPy" or sys_platform == "win32") and extra == "test"
Provides-Extra: docs
Requires-Dist: sphinx; extra == "docs"
Requires-Dist: sphinxcontrib-programoutput; extra == "docs"
Requires-Dist: repoze.sphinx.autointerface; extra == "docs"
Requires-Dist: sphinx_rtd_theme; extra == "docs"
Requires-Dist: ZEO; extra == "docs"
Requires-Dist: furo; extra == "docs"
Provides-Extra: all-tested-drivers
Requires-Dist: PyMySQL>=0.6.6; python_version == "3.9" and extra == "all-tested-drivers"
Requires-Dist: mysqlclient>=2.0.0; extra == "all-tested-drivers"
Requires-Dist: mysql-connector-python>=9.2.0; python_version == "3.10" and extra == "all-tested-drivers"
Requires-Dist: pg8000>=1.29.0; python_version == "3.11" and extra == "all-tested-drivers"
Requires-Dist: psycopg2cffi>=2.7.4; (python_version == "3.11" or platform_python_implementation == "PyPy") and extra == "all-tested-drivers"
Requires-Dist: psycopg2>=2.8.3; platform_python_implementation == "CPython" and extra == "all-tested-drivers"
Dynamic: author
Dynamic: author-email
Dynamic: classifier
Dynamic: description
Dynamic: home-page
Dynamic: keywords
Dynamic: license
Dynamic: license-file
Dynamic: maintainer
Dynamic: maintainer-email
Dynamic: platform
Dynamic: project-url
Dynamic: provides-extra
Dynamic: requires-dist
Dynamic: requires-python
Dynamic: summary
